odoo10_addon_base_sparse_field_list_support-10.0.1.0.0.99.dev7-py3.8-nspkg.pth
odoo/addons/base_sparse_field_list_support/README.rst
odoo/addons/base_sparse_field_list_support/__init__.py
odoo/addons/base_sparse_field_list_support/__manifest__.py
odoo/addons/base_sparse_field_list_support/i18n/base_sparse_field_list_support.pot
odoo/addons/base_sparse_field_list_support/models/__init__.py
odoo/addons/base_sparse_field_list_support/models/fields.py
odoo10_addon_base_sparse_field_list_support-10.0.1.0.0.99.dev7.dist-info/METADATA
odoo10_addon_base_sparse_field_list_support-10.0.1.0.0.99.dev7.dist-info/WHEEL
odoo10_addon_base_sparse_field_list_support-10.0.1.0.0.99.dev7.dist-info/namespace_packages.txt
odoo10_addon_base_sparse_field_list_support-10.0.1.0.0.99.dev7.dist-info/top_level.txt
odoo10_addon_base_sparse_field_list_support-10.0.1.0.0.99.dev7.dist-info/RECORD
