Metadata-Version: 2.1
Name: odoo10-addon-base-sparse-field-list-support
Version: 10.0.1.0.0.99.dev7
Summary: add list support to convert_to_cache()
Home-page: https://github.com/shopinvader/odoo-misc
Author: Akretion
License: AGPL-3
Platform: UNKNOWN
Classifier: Programming Language :: Python
Classifier: Framework :: Odoo
Classifier: License :: OSI Approved :: GNU Affero General Public License v3
Requires-Python: ~=2.7
Requires-Dist: odoo (<10.1dev,>=10.0)
